etc/intelmq/api-apache.conf
etc/intelmq/api-config.json
etc/intelmq/api-sudoers.conf
etc/intelmq/intelmq-api.service
etc/intelmq/intelmq-api.socket
etc/intelmq/manager/positions.conf
intelmq_api/__init__.py
intelmq_api/api.py
intelmq_api/config.py
intelmq_api/dependencies.py
intelmq_api/exceptions.py
intelmq_api/files.py
intelmq_api/main.py
intelmq_api/models.py
intelmq_api/runctl.py
intelmq_api/session.py
intelmq_api/util.py
intelmq_api/version.py
intelmq_api-3.2.0.data/scripts/intelmq-api-adduser
intelmq_api-3.2.0.data/scripts/intelmq-api-setup-systemd
tests/__init__.py
tests/test_api.py
tests/test_sessionstore.py
intelmq_api-3.2.0.dist-info/METADATA
intelmq_api-3.2.0.dist-info/WHEEL
intelmq_api-3.2.0.dist-info/top_level.txt
intelmq_api-3.2.0.dist-info/RECORD
