Metadata-Version: 2.1
Name: intelmq-api
Version: 3.2.0
Summary: Intelmq-API is a FastAPI based API to intelmq, a solution for IT security teams for collecting and processing security feeds
Home-page: https://github.com/certtools/intelmq-api
Requires-Python: >=3.7
Requires-Dist: fastapi (>=0.63.0)
Requires-Dist: intelmq (>=2.2.3)
Requires-Dist: python-multipart
Requires-Dist: typing-extensions (>=3.10.0.0)
Requires-Dist: uvicorn[standard] (>=0.20.0)
Provides-Extra: dev
Requires-Dist: httpx ; extra == 'dev'
Requires-Dist: pycodestyle (>=2.10.0) ; extra == 'dev'
